nuchabal-0.1.5.dist-info/METADATA
nuchabal-0.1.5.dist-info/WHEEL
nuchabal-0.1.5.dist-info/entry_points.txt
nuchabäl/__init__.py
nuchabäl/retamabäl/ch'ab'äl.json
nuchabäl/retamabäl/tzib'.json
nuchabäl/rujaloxïk.py
nuchabäl/rujaloxïkChumil.py
nuchabäl/rukux.py
nuchabal-0.1.5.dist-info/RECORD
